{"watchingStocks": [{"sinaSymbol": "sz002075", "type": "11", "name": "沙钢股份", "picked": false}, {"sinaSymbol": "sh600811", "type": "11", "name": "东方集团", "picked": false}, {"sinaSymbol": "sz000729", "type": "11", "name": "燕京啤酒", "picked": false}, {"sinaSymbol": "sz002852", "type": "11", "name": "道道全", "picked": false}, {"sinaSymbol": "sh601368", "type": "11", "name": "绿城水务", "picked": false}, {"sinaSymbol": "sz000731", "type": "11", "name": "四川美丰", "picked": false}, {"sinaSymbol": "sh600833", "type": "11", "name": "第一医药", "picked": false}, {"sinaSymbol": "sz300529", "type": "11", "name": "健帆生物", "picked": false}]}