{"watchingStocks": [{"sinaSymbol": "sz002508", "type": "11", "name": "老板电器", "picked": false, "sellPrice": null}, {"sinaSymbol": "sz000637", "type": "11", "name": "茂化实华", "picked": false, "sellPrice": null}, {"sinaSymbol": "sz002849", "type": "11", "name": "威星智能", "picked": false, "sellPrice": null}, {"sinaSymbol": "sh600063", "type": "11", "name": "皖维高新", "picked": false, "sellPrice": null}, {"sinaSymbol": "sh603100", "type": "11", "name": "川仪股份", "picked": false, "sellPrice": null}, {"sinaSymbol": "sz002580", "type": "11", "name": "圣阳股份", "picked": false, "sellPrice": null}, {"sinaSymbol": "sh600749", "type": "11", "name": "西藏旅游", "picked": false, "sellPrice": null}, {"sinaSymbol": "sh600875", "type": "11", "name": "东方电气", "picked": false, "sellPrice": null}, {"sinaSymbol": "sh600477", "type": "11", "name": "杭萧钢构", "picked": false, "sellPrice": null}, {"sinaSymbol": "sh603050", "type": "11", "name": "科林电气", "picked": false, "sellPrice": null}, {"sinaSymbol": "sz300154", "type": "11", "name": "瑞凌股份", "picked": false, "sellPrice": null}, {"sinaSymbol": "sz002433", "type": "11", "name": "太安堂", "picked": false, "sellPrice": null}, {"sinaSymbol": "sz002053", "type": "11", "name": "云南能投", "picked": false, "sellPrice": null}, {"sinaSymbol": "sz002364", "type": "11", "name": "中恒电气", "picked": false, "sellPrice": null}, {"sinaSymbol": "sh600773", "type": "11", "name": "西藏城投", "picked": false, "sellPrice": null}, {"sinaSymbol": "sz002475", "type": "11", "name": "立讯精密", "picked": false, "sellPrice": null}, {"sinaSymbol": "sz000028", "type": "11", "name": "国药一致", "picked": false, "sellPrice": null}, {"sinaSymbol": "sz002537", "type": "11", "name": "海联金汇", "picked": false, "sellPrice": null}, {"sinaSymbol": "sh603123", "type": "11", "name": "翠微股份", "picked": false, "sellPrice": null}, {"sinaSymbol": "sh600603", "type": "11", "name": "广汇物流", "picked": false, "sellPrice": null}, {"sinaSymbol": "sz000638", "type": "11", "name": "万方发展", "picked": false, "sellPrice": null}]}