{"watchingStocks": [{"sinaSymbol": "sh603017", "type": "11", "name": "中衡设计", "picked": false, "sellPrice": null}, {"sinaSymbol": "sz300022", "type": "11", "name": "吉峰科技", "picked": false, "sellPrice": null}, {"sinaSymbol": "sz002546", "type": "11", "name": "新联电子", "picked": false, "sellPrice": null}, {"sinaSymbol": "sz300135", "type": "11", "name": "宝利国际", "picked": false, "sellPrice": null}, {"sinaSymbol": "sh600811", "type": "11", "name": "东方集团", "picked": false, "sellPrice": null}, {"sinaSymbol": "sh600249", "type": "11", "name": "两面针", "picked": false, "sellPrice": null}, {"sinaSymbol": "sz000735", "type": "11", "name": "罗牛山", "picked": false, "sellPrice": null}, {"sinaSymbol": "sh600982", "type": "11", "name": "宁波热电", "picked": false, "sellPrice": null}, {"sinaSymbol": "sz300201", "type": "11", "name": "海伦哲", "picked": false, "sellPrice": null}, {"sinaSymbol": "sz300710", "type": "11", "name": "万隆光电", "picked": false, "sellPrice": null}, {"sinaSymbol": "sz002931", "type": "11", "name": "锋龙股份", "picked": false, "sellPrice": null}, {"sinaSymbol": "sh600960", "type": "11", "name": "渤海汽车", "picked": false, "sellPrice": null}, {"sinaSymbol": "sh603088", "type": "11", "name": "宁波精达", "picked": false, "sellPrice": null}]}