{"watchingStocks": [{"sinaSymbol": "sh603678", "type": "11", "name": "火炬电子", "picked": false, "targetPrice": 49.1, "sellPrice": null}, {"sinaSymbol": "sh603990", "type": "11", "name": "麦迪科技", "picked": false, "targetPrice": 45.29999999999999, "sellPrice": null}, {"sinaSymbol": "sh603259", "type": "11", "name": "药明康德", "picked": false, "targetPrice": 111.8, "sellPrice": null}, {"sinaSymbol": "sz002653", "type": "11", "name": "海思科", "picked": false, "targetPrice": 24.66, "sellPrice": null}, {"sinaSymbol": "sz002735", "type": "11", "name": "王子新材", "picked": false, "targetPrice": 43.27000000000001, "sellPrice": null}, {"sinaSymbol": "sz000885", "type": "11", "name": "城发环境", "picked": false, "targetPrice": 11.21, "sellPrice": null}, {"sinaSymbol": "sz002367", "type": "11", "name": "康力电梯", "picked": false, "targetPrice": 12.24, "sellPrice": null}, {"sinaSymbol": "sz300568", "type": "11", "name": "星源材质", "picked": false, "targetPrice": 24.12, "sellPrice": null}, {"sinaSymbol": "sz300124", "type": "11", "name": "汇川技术", "picked": false, "targetPrice": 64.66000000000001, "sellPrice": null}, {"sinaSymbol": "sh600156", "type": "11", "name": "华升股份", "picked": false, "targetPrice": 5.19, "sellPrice": null}, {"sinaSymbol": "sh603015", "type": "11", "name": "弘讯科技", "picked": false, "targetPrice": 8.0, "sellPrice": null}, {"sinaSymbol": "sz300014", "type": "11", "name": "亿纬锂能", "picked": false, "targetPrice": 57.16, "sellPrice": null}, {"sinaSymbol": "sh600967", "type": "11", "name": "内蒙一机", "picked": false, "targetPrice": 11.74, "sellPrice": null}, {"sinaSymbol": "sz300548", "type": "11", "name": "博创科技", "picked": false, "targetPrice": 51.76, "sellPrice": null}, {"sinaSymbol": "sz002335", "type": "11", "name": "科华恒盛", "picked": false, "targetPrice": 22.85, "sellPrice": null}, {"sinaSymbol": "sz300677", "type": "11", "name": "英科医疗", "picked": false, "targetPrice": 119.00000000000004, "sellPrice": null}, {"sinaSymbol": "sz002568", "type": "11", "name": "百润股份", "picked": false, "targetPrice": 68.26, "sellPrice": null}, {"sinaSymbol": "sz002623", "type": "11", "name": "亚玛顿", "picked": false, "targetPrice": 45.21, "sellPrice": null}, {"sinaSymbol": "sz300363", "type": "11", "name": "博腾股份", "picked": false, "targetPrice": 40.29999999999999, "sellPrice": null}, {"sinaSymbol": "sh603127", "type": "11", "name": "昭衍新药", "picked": false, "targetPrice": 107.77000000000001, "sellPrice": null}]}