{"watchingStocks": [{"sinaSymbol": "sz002133", "type": "11", "name": "广宇集团", "picked": false, "targetPrice": 3.37, "sellPrice": null}, {"sinaSymbol": "sz300708", "type": "11", "name": "聚灿光电", "picked": false, "targetPrice": 18.48, "sellPrice": null}, {"sinaSymbol": "sz300467", "type": "11", "name": "迅游科技", "picked": false, "targetPrice": 18.53, "sellPrice": null}, {"sinaSymbol": "sh600246", "type": "11", "name": "万通地产", "picked": false, "targetPrice": 9.480000000000002, "sellPrice": null}, {"sinaSymbol": "sh600201", "type": "11", "name": "生物股份", "picked": false, "targetPrice": 31.149999999999995, "sellPrice": null}, {"sinaSymbol": "sh601021", "type": "11", "name": "春秋航空", "picked": false, "targetPrice": 45.50000000000001, "sellPrice": null}, {"sinaSymbol": "sh600293", "type": "11", "name": "三峡新材", "picked": false, "targetPrice": 2.9499999999999997, "sellPrice": null}, {"sinaSymbol": "sz002856", "type": "11", "name": "美芝股份", "picked": false, "targetPrice": 17.95, "sellPrice": null}, {"sinaSymbol": "sh603919", "type": "11", "name": "金徽酒", "picked": false, "targetPrice": 19.38, "sellPrice": null}, {"sinaSymbol": "sz002484", "type": "11", "name": "江海股份", "picked": false, "targetPrice": 11.5, "sellPrice": null}, {"sinaSymbol": "sz300632", "type": "11", "name": "光莆股份", "picked": false, "targetPrice": 19.399999999999995, "sellPrice": null}, {"sinaSymbol": "sh600888", "type": "11", "name": "新疆众和", "picked": false, "targetPrice": 5.95, "sellPrice": null}, {"sinaSymbol": "sh600345", "type": "11", "name": "长江通信", "picked": false, "targetPrice": 21.72, "sellPrice": null}, {"sinaSymbol": "sz002384", "type": "11", "name": "东山精密", "picked": false, "targetPrice": 30.430000000000003, "sellPrice": null}, {"sinaSymbol": "sh600106", "type": "11", "name": "重庆路桥", "picked": false, "targetPrice": 2.79, "sellPrice": null}, {"sinaSymbol": "sh600563", "type": "11", "name": "法拉电子", "picked": false, "targetPrice": 68.95, "sellPrice": null}, {"sinaSymbol": "sz002197", "type": "11", "name": "证通电子", "picked": false, "targetPrice": 11.570000000000002, "sellPrice": null}, {"sinaSymbol": "sz002649", "type": "11", "name": "博彦科技", "picked": false, "targetPrice": 11.380000000000003, "sellPrice": null}, {"sinaSymbol": "sh603429", "type": "11", "name": "集友股份", "picked": false, "targetPrice": 40.96, "sellPrice": null}, {"sinaSymbol": "sh603111", "type": "11", "name": "康尼机电", "picked": false, "targetPrice": 7.239999999999998, "sellPrice": null}]}